Metadata-Version: 2.1
Name: zoomeye-hk
Version: 2.2.0
Summary: Python library and command-line tool for ZoomEye (https://www.zoomeye.hk/doc)
Home-page: https://github.com/zoomeye-hk/zoomeye-python
Author: ZoomEye.HK
Keywords: security tool,zoomeye,command tool
Classifier: Development Status :: 5 - Production/Stable
Classifier: Intended Audience :: Developers
Classifier: License :: OSI Approved :: MIT License
Classifier: Natural Language :: English
Classifier: Operating System :: OS Independent
Classifier: Programming Language :: Python :: 3
Classifier: Programming Language :: Python :: 3.5
Classifier: Programming Language :: Python :: 3.6
Classifier: Programming Language :: Python :: 3.7
Classifier: Programming Language :: Python :: 3.8
Classifier: Programming Language :: Python :: 3.9
Classifier: Topic :: Software Development :: Libraries :: Python Modules
License-File: LICENSE
Requires-Dist: certifi ==2021.10.8
Requires-Dist: charset-normalizer ==2.0.8
Requires-Dist: colorama ==0.4.4
Requires-Dist: graphviz ==0.19
Requires-Dist: idna ==3.3
Requires-Dist: requests ==2.26.0
Requires-Dist: urllib3 ==1.26.7
